space/agent.py
space/llm.py
space/main.py
space/mcp.py
space/memory.py
space/project.py
space/prompts.py
space/tools.py
space/ui.py
space/web.py
space_agent-0.1.1.dist-info/METADATA
space_agent-0.1.1.dist-info/WHEEL
space_agent-0.1.1.dist-info/entry_points.txt
space_agent-0.1.1.dist-info/top_level.txt
space_agent-0.1.1.dist-info/RECORD
