Metadata-Version: 2.4
Name: space-agent
Version: 0.1.1
Summary: Space: A powerful, fully local CLI coding assistant powered by Ollama.
Requires-Python: >=3.12
Requires-Dist: crawl4ai>=0.7.8
Requires-Dist: ddgs>=9.10.0
Requires-Dist: mcp>=1.25.0
Requires-Dist: ollama>=0.6.1
Requires-Dist: prompt-toolkit>=3.0.52
Requires-Dist: rich>=14.2.0
Requires-Dist: typer>=0.21.0
